canliicalls/__init__.py
canliicalls/_modidx.py
canliicalls/caller.py
canliicalls-0.0.1.dist-info/LICENSE
canliicalls-0.0.1.dist-info/METADATA
canliicalls-0.0.1.dist-info/WHEEL
canliicalls-0.0.1.dist-info/entry_points.txt
canliicalls-0.0.1.dist-info/top_level.txt
canliicalls-0.0.1.dist-info/RECORD
