Metadata-Version: 2.1
Name: canliicalls
Version: 0.0.1
Summary: Interact with CanLII programmatically
Home-page: https://github.com/simon-lawyer/canliicalls
Author: Simon Wallace
Author-email: simonwallace@osgoode.yorku.ca
License: Apache Software License 2.0
Keywords: nbdev jupyter notebook python
Classifier: Development Status :: 4 - Beta
Classifier: Intended Audience :: Education
Classifier: Natural Language :: English
Classifier: Programming Language :: Python :: 3.7
Classifier: Programming Language :: Python :: 3.8
Classifier: Programming Language :: Python :: 3.9
Classifier: Programming Language :: Python :: 3.10
Classifier: License :: OSI Approved :: Apache Software License
Requires-Python: >=3.7
License-File: LICENSE
Requires-Dist: fastcore
Requires-Dist: pandas
Requires-Dist: requests
Provides-Extra: dev
